dragontide/__init__.py
dragontide/_decorators.py
dragontide/_elements.py
dragontide/_grammars.py
dragontide/_rules.py
dragontide/_specparsers.py
dragontide/_support.py
dragontide-1.0.0.dist-info/LICENSE.txt
dragontide-1.0.0.dist-info/METADATA
dragontide-1.0.0.dist-info/WHEEL
dragontide-1.0.0.dist-info/top_level.txt
dragontide-1.0.0.dist-info/RECORD
