Metadata-Version: 2.1
Name: dragontide
Version: 1.0.0
Summary: CCR extension to Dragonfly
Home-page: https://github.com/dsw88/dragontide
Author: David Woodruff
Author-email: themaplewoods@outlook.com
License: Unilicense
Keywords: continuous command recognition,speech recognition,voice coding,dragonfly,Dragon
Platform: UNKNOWN
Classifier: Development Status :: 3 - Alpha
Classifier: Intended Audience :: Developers
Classifier: License :: Public Domain
Classifier: Programming Language :: Python
Classifier: Programming Language :: Python :: 3 :: Only
Classifier: Topic :: Adaptive Technologies
Classifier: Topic :: Software Development :: Libraries
Classifier: Topic :: Software Development :: Libraries :: Python Modules
Requires-Dist: dragonfly2 (>=0.30.0)
